{
    "slug": "whistle-pig-limited",
    "title": "Sell WhistlePig Boss Hog",
    "metaTitle": "Sell WhistlePig Boss Hog & Rare Rye | Proof Cellars",
    "metaDescription": "Sell your WhistlePig Boss Hog collection. We buy Boss Hog I-X, 12 Year, 15 Year, and 18 Year Single Malt. Direct offers.",
    "heroHeadline": "Sell WhistlePig Boss Hog",
    "heroSubhead": "We buy the complete WhistlePig Boss Hog series and limited ryes.",
    "introParagraph": "WhistlePig Boss Hog is the premier annual release of Canadian/American rye whiskey, known for unique finishes and pewter toppers. We purchase the entire Boss Hog series (Editions I through X and beyond) as well as older age-stated releases. Sell your WhistlePig collection directly for a competitive price.",
    "categoryType": "bourbon",
    "whatWeBuy": [
        "WhistlePig Boss Hog (Editions I - X)",
        "WhistlePig 111 Proof (older release)",
        "WhistlePig 12 Year Old World (older batches)",
        "WhistlePig 15 Year Estate Oak",
        "WhistlePig 18 Year Double Malt",
        "WhistlePig Behold & Bespoke"
    ],
    "whatWeDoNotBuy": [
        "Standard WhistlePig 10 Year",
        "WhistlePig PiggyBack 6 Year",
        "WhistlePig FarmStock (recent batches)",
        "Opened bottles",
        "Bottles with missing toppers (for Boss Hog)"
    ],
    "photoChecklist": [
        "Front label identifying the Edition (e.g., Samurai Scientist, Magellan's Atlantic)",
        "Pewter topper condition",
        "Original box condition",
        "Fill level",
        "Any cracks in the wax (if applicable)"
    ],
    "conditionFactors": [
        "The pewter topper is essential for full value on Boss Hog",
        "Original box condition",
        "Label condition",
        "Fill level"
    ],
    "pricingFactors": [
        "Edition number (Boss Hog I, II, III are significantly more valuable)",
        "Completeness (topper + box)",
        "Market demand for specific finishes"
    ],
    "faqs": [
        {
            "question": "Do I need the pewter topper?",
            "answer": "Yes, for Boss Hog releases, the unique pewter topper is a critical part of the value. Missing toppers significantly reduce the offer."
        },
        {
            "question": "Which Boss Hog is most valuable?",
            "answer": "Generally, the earlier releases (Boss Hog I: Spice Dancer, II: Spirit of Mortimer) command the highest prices."
        },
        {
            "question": "Do you buy WhistlePig 10 Year?",
            "answer": "We typically do not buy standard 10 Year unless it is an older '10/100' release or a special single barrel store pick."
        },
        {
            "question": "Do you buy the 18 Year Double Malt?",
            "answer": "Yes, we purchase the 18 Year and other premium age-stated releases."
        },
        {
            "question": "How do I ship the Boss Hog box?",
            "answer": "The black display boxes are sturdy but can scuff. Wrap the entire box in bubble wrap before placing it in the shipping carton."
        },
        {
            "question": "Do you buy WhistlePig FarmStock?",
            "answer": "We generally do not buy recent FarmStock batches unless part of a larger collection."
        }
    ],
    "relatedLinks": [
        {
            "label": "Get an Offer",
            "href": "/get-offer"
        },
        {
            "label": "Sell High West",
            "href": "/sell/high-west-limited"
        },
        {
            "label": "Sell Bourbon",
            "href": "/sell/bourbon"
        },
        {
            "label": "Packing Guide",
            "href": "/resources/packing-guide"
        }
    ]
}